rspypiHelloWorld/__init__.py
rspypiHelloWorld/hello.py
rspypiHelloWorld-1.0.0.dist-info/LICENCE
rspypiHelloWorld-1.0.0.dist-info/METADATA
rspypiHelloWorld-1.0.0.dist-info/WHEEL
rspypiHelloWorld-1.0.0.dist-info/entry_points.txt
rspypiHelloWorld-1.0.0.dist-info/top_level.txt
rspypiHelloWorld-1.0.0.dist-info/RECORD
